src/__init__.py
src/plugin.py
mkdocs_img2figv2_plugin-0.0.2.dist-info/LICENSE
mkdocs_img2figv2_plugin-0.0.2.dist-info/METADATA
mkdocs_img2figv2_plugin-0.0.2.dist-info/WHEEL
mkdocs_img2figv2_plugin-0.0.2.dist-info/entry_points.txt
mkdocs_img2figv2_plugin-0.0.2.dist-info/top_level.txt
mkdocs_img2figv2_plugin-0.0.2.dist-info/RECORD
