Metadata-Version: 2.1
Name: mkdocs-img2figv2-plugin
Version: 0.0.2
Summary: A MkDocs plugin that converts markdown encoded images into <figure> elements.
Home-page: https://github.com/jackiexiao/mkdocs-img2figv2-plugin
Author: Antonio Cambule & jackiexiao
License: MIT
Keywords: mkdocs python markdown
Platform: UNKNOWN
Requires-Python: >=3.6
Requires-Dist: mkdocs
